ds2/__init__.py
ds2/deque/__init__.py
ds2/deque/doublylinkedlist.py
ds2/deque/linkedlist.py
ds2/deque/listdeque.py
ds2/disjointsets/__init__.py
ds2/disjointsets/disjointsets.py
ds2/figs/__init__.py
ds2/figs/drawing.py
ds2/figure_generation/__init__.py
ds2/figure_generation/draw_binarytree.py
ds2/figure_generation/drawgraph.py
ds2/figure_generation/drawing.py
ds2/figure_generation/drawlist.py
ds2/figure_generation/drawtrees.py
ds2/figure_generation/svghelper.py
ds2/graph/__init__.py
ds2/graph/adjacencysetgraph.py
ds2/graph/digraph.py
ds2/graph/edgesetgraph.py
ds2/graph/graph.py
ds2/graph/graphsearch.py
ds2/graph/kruskall.py
ds2/graph/undirectedadjacencysetgraph.py
ds2/mapping/__init__.py
ds2/mapping/hashmapping.py
ds2/mapping/hashmapping_notDRY.py
ds2/mapping/hashmappingsimple.py
ds2/mapping/listmapping.py
ds2/mapping/listmapping_notDRY.py
ds2/mapping/listmappingsimple.py
ds2/mapping/mapping.py
ds2/orderedlist/__init__.py
ds2/orderedlist/orderedlist.py
ds2/orderedlist/orderedlistsimple.py
ds2/orderedmapping/__init__.py
ds2/orderedmapping/avltree.py
ds2/orderedmapping/balancedbst.py
ds2/orderedmapping/bstmapping.py
ds2/orderedmapping/splaytree.py
ds2/orderedmapping/wbtree.py
ds2/priorityqueue/__init__.py
ds2/priorityqueue/entry.py
ds2/priorityqueue/heappq.py
ds2/priorityqueue/priorityqueue.py
ds2/priorityqueue/simplelistpq.py
ds2/priorityqueue/sortedlistpq.py
ds2/priorityqueue/unsortedlistpq.py
ds2/queue/__init__.py
ds2/queue/linkedqueue.py
ds2/queue/listqueue.py
ds2/select/__init__.py
ds2/select/quickselect.py
ds2/select/quickselect_recursive.py
ds2/sorting/__init__.py
ds2/sorting/bubblesort.py
ds2/sorting/bubblesortsimple.py
ds2/sorting/dumbsort.py
ds2/sorting/heapsort.py
ds2/sorting/insertionsort.py
ds2/sorting/insertionsortsimple.py
ds2/sorting/mergesort.py
ds2/sorting/mergesort_iter.py
ds2/sorting/quicksort.py
ds2/sorting/quicksort_long.py
ds2/sorting/selectionsort.py
ds2/stack/__init__.py
ds2/stack/anotherstack.py
ds2/stack/badstack.py
ds2/stack/liststack.py
ds2-0.2.4.dist-info/LICENSE
ds2-0.2.4.dist-info/METADATA
ds2-0.2.4.dist-info/WHEEL
ds2-0.2.4.dist-info/top_level.txt
ds2-0.2.4.dist-info/RECORD
