Metadata-Version: 2.1
Name: ds2
Version: 0.2.4
Summary: Don Sheehy's Data Structures
Home-page: https://github.com/donsheehy/datastructures
Author: Donald R. Sheehy
Author-email: don.r.sheehy@gmail.com
Classifier: Programming Language :: Python :: 3
Classifier: License :: OSI Approved :: MIT License
Classifier: Operating System :: OS Independent
Requires-Python: >=3.6
License-File: LICENSE
